pyfatx-0.0.7.dist-info/WHEEL
pyfatx-0.0.7.dist-info/top_level.txt
pyfatx-0.0.7.dist-info/LICENSE.txt
pyfatx-0.0.7.dist-info/METADATA
pyfatx-0.0.7.dist-info/RECORD
pyfatx/libfatx.cpython-38-x86_64-linux-gnu.so
pyfatx/__main__.py
pyfatx/__init__.py
